{
  "gitSyncId": "66ec903bbf3458523e79593d_de634e62-f958-400b-b0a5-dcb25154c69a",
  "id": "Page1_calcolaFlussi.getLinesFromBase64File",
  "pluginId": "js-plugin",
  "pluginType": "JS",
  "unpublishedAction": {
    "actionConfiguration": {
      "encodeParamsToggle": true,
      "jsArguments": [
        {
          "name": "text"
        }
      ],
      "paginationType": "NONE",
      "timeoutInMillisecond": 10000
    },
    "collectionId": "Page1_calcolaFlussi",
    "confirmBeforeExecute": false,
    "datasource": {
      "isAutoGenerated": false,
      "name": "UNUSED_DATASOURCE",
      "pluginId": "js-plugin"
    },
    "dynamicBindingPathList": [
      {
        "key": "body"
      }
    ],
    "executeOnLoad": false,
    "fullyQualifiedName": "calcolaFlussi.getLinesFromBase64File",
    "name": "getLinesFromBase64File",
    "pageId": "Page1",
    "userSetOnLoad": false
  }
}