{
  "gitSyncId": "66ec903bbf3458523e79593d_a54c11d3-a593-4682-b62a-766cf6b88a97",
  "id": "Page1_calcolaFlussi._loadStruttureFromFlowlookDB",
  "pluginId": "js-plugin",
  "pluginType": "JS",
  "unpublishedAction": {
    "actionConfiguration": {
      "encodeParamsToggle": true,
      "jsArguments": [],
      "paginationType": "NONE",
      "timeoutInMillisecond": 10000
    },
    "collectionId": "Page1_calcolaFlussi",
    "confirmBeforeExecute": false,
    "datasource": {
      "isAutoGenerated": false,
      "name": "UNUSED_DATASOURCE",
      "pluginId": "js-plugin"
    },
    "dynamicBindingPathList": [
      {
        "key": "body"
      }
    ],
    "executeOnLoad": false,
    "fullyQualifiedName": "calcolaFlussi._loadStruttureFromFlowlookDB",
    "name": "_loadStruttureFromFlowlookDB",
    "pageId": "Page1",
    "userSetOnLoad": false
  }
}